discord_logging/__init__.py
discord_logging/discord_logging.py
discord_logging-1.0.dist-info/METADATA
discord_logging-1.0.dist-info/WHEEL
discord_logging-1.0.dist-info/top_level.txt
discord_logging-1.0.dist-info/RECORD
